arcade_search/__init__.py
arcade_search/constants.py
arcade_search/enums.py
arcade_search/exceptions.py
arcade_search/google_data.py
arcade_search/utils.py
arcade_search/tools/__init__.py
arcade_search/tools/google_finance.py
arcade_search/tools/google_flights.py
arcade_search/tools/google_hotels.py
arcade_search/tools/google_jobs.py
arcade_search/tools/google_maps.py
arcade_search/tools/google_news.py
arcade_search/tools/google_search.py
arcade_search/tools/google_shopping.py
arcade_search/tools/walmart.py
arcade_search/tools/youtube.py
arcade_search-2.0.1.dist-info/METADATA
arcade_search-2.0.1.dist-info/WHEEL
arcade_search-2.0.1.dist-info/licenses/LICENSE
arcade_search-2.0.1.dist-info/RECORD
